[
    {
        "key": "datr",
        "value": "ulu6aHpm2ujO29FSmMRTsjXe",
        "domain": "facebook.com",
        "path": "/",
        "hostOnly": false,
        "creation": "2025-09-12T16:29:17.794Z",
        "lastAccessed": "2025-09-12T16:29:17.794Z"
    },
    {
        "key": "sb",
        "value": "ulu6aPNfELw3atEviCSm4s36",
        "domain": "facebook.com",
        "path": "/",
        "hostOnly": false,
        "creation": "2025-09-12T16:29:17.794Z",
        "lastAccessed": "2025-09-12T16:29:17.794Z"
    },
    {
        "key": "ps_l",
        "value": "1",
        "domain": "facebook.com",
        "path": "/",
        "hostOnly": false,
        "creation": "2025-09-12T16:29:17.794Z",
        "lastAccessed": "2025-09-12T16:29:17.794Z"
    },
    {
        "key": "ps_n",
        "value": "1",
        "domain": "facebook.com",
        "path": "/",
        "hostOnly": false,
        "creation": "2025-09-12T16:29:17.794Z",
        "lastAccessed": "2025-09-12T16:29:17.794Z"
    },
    {
        "key": "vpd",
        "value": "v1%3B710x360x2",
        "domain": "facebook.com",
        "path": "/",
        "hostOnly": false,
        "creation": "2025-09-12T16:29:17.794Z",
        "lastAccessed": "2025-09-12T16:29:17.794Z"
    },
    {
        "key": "pas",
        "value": "61579153288875%3AHAFeP6cu2W",
        "domain": "facebook.com",
        "path": "/",
        "hostOnly": false,
        "creation": "2025-09-12T16:29:17.794Z",
        "lastAccessed": "2025-09-12T16:29:17.794Z"
    },
    {
        "key": "locale",
        "value": "en_GB",
        "domain": "facebook.com",
        "path": "/",
        "hostOnly": false,
        "creation": "2025-09-12T16:29:17.794Z",
        "lastAccessed": "2025-09-12T16:29:17.794Z"
    },
    {
        "key": "m_pixel_ratio",
        "value": "2",
        "domain": "facebook.com",
        "path": "/",
        "hostOnly": false,
        "creation": "2025-09-12T16:29:17.794Z",
        "lastAccessed": "2025-09-12T16:29:17.794Z"
    },
    {
        "key": "wd",
        "value": "360x806",
        "domain": "facebook.com",
        "path": "/",
        "hostOnly": false,
        "creation": "2025-09-12T16:29:17.794Z",
        "lastAccessed": "2025-09-12T16:29:17.794Z"
    },
    {
        "key": "c_user",
        "value": "61579153288875",
        "domain": "facebook.com",
        "path": "/",
        "hostOnly": false,
        "creation": "2025-09-12T16:29:17.794Z",
        "lastAccessed": "2025-09-12T16:29:17.794Z"
    },
    {
        "key": "xs",
        "value": "9%3AV0DKFW-srR-MFg%3A2%3A1757694549%3A-1%3A-1",
        "domain": "facebook.com",
        "path": "/",
        "hostOnly": false,
        "creation": "2025-09-12T16:29:17.794Z",
        "lastAccessed": "2025-09-12T16:29:17.794Z"
    },
    {
        "key": "fr",
        "value": "0pVNczGSD5h070cwJ.AWeaWC5Wvhn8UrjZb2imrwMXaP2Rfn6t12Ta5ind8IX6SAbpBWQ.Boulu6..AAA.0.0.BoxEpX.AWdHYmPtfjpcdd_Rt-WN_UT4Wog",
        "domain": "facebook.com",
        "path": "/",
        "hostOnly": false,
        "creation": "2025-09-12T16:29:17.794Z",
        "lastAccessed": "2025-09-12T16:29:17.794Z"
    },
    {
        "key": "fbl_st",
        "value": "101327901%3BT%3A29294909",
        "domain": "facebook.com",
        "path": "/",
        "hostOnly": false,
        "creation": "2025-09-12T16:29:17.794Z",
        "lastAccessed": "2025-09-12T16:29:17.794Z"
    },
    {
        "key": "wl_cbv",
        "value": "v2%3Bclient_version%3A2921%3Btimestamp%3A1757694552",
        "domain": "facebook.com",
        "path": "/",
        "hostOnly": false,
        "creation": "2025-09-12T16:29:17.794Z",
        "lastAccessed": "2025-09-12T16:29:17.794Z"
    }
]
