[
    {
        "key": "datr",
        "value": "ulu6aHpm2ujO29FSmMRTsjXe",
        "domain": "facebook.com",
        "path": "/",
        "hostOnly": false,
        "creation": "2025-09-10T11:41:03.681Z",
        "lastAccessed": "2025-09-10T11:41:03.681Z"
    },
    {
        "key": "sb",
        "value": "ulu6aPNfELw3atEviCSm4s36",
        "domain": "facebook.com",
        "path": "/",
        "hostOnly": false,
        "creation": "2025-09-10T11:41:03.681Z",
        "lastAccessed": "2025-09-10T11:41:03.681Z"
    },
    {
        "key": "ps_l",
        "value": "1",
        "domain": "facebook.com",
        "path": "/",
        "hostOnly": false,
        "creation": "2025-09-10T11:41:03.681Z",
        "lastAccessed": "2025-09-10T11:41:03.681Z"
    },
    {
        "key": "ps_n",
        "value": "1",
        "domain": "facebook.com",
        "path": "/",
        "hostOnly": false,
        "creation": "2025-09-10T11:41:03.681Z",
        "lastAccessed": "2025-09-10T11:41:03.681Z"
    },
    {
        "key": "locale",
        "value": "en_GB",
        "domain": "facebook.com",
        "path": "/",
        "hostOnly": false,
        "creation": "2025-09-10T11:41:03.681Z",
        "lastAccessed": "2025-09-10T11:41:03.681Z"
    },
    {
        "key": "vpd",
        "value": "v1%3B710x360x2",
        "domain": "facebook.com",
        "path": "/",
        "hostOnly": false,
        "creation": "2025-09-10T11:41:03.682Z",
        "lastAccessed": "2025-09-10T11:41:03.682Z"
    },
    {
        "key": "pas",
        "value": "61579153288875%3AHAFeP6cu2W",
        "domain": "facebook.com",
        "path": "/",
        "hostOnly": false,
        "creation": "2025-09-10T11:41:03.682Z",
        "lastAccessed": "2025-09-10T11:41:03.682Z"
    },
    {
        "key": "c_user",
        "value": "61579153288875",
        "domain": "facebook.com",
        "path": "/",
        "hostOnly": false,
        "creation": "2025-09-10T11:41:03.682Z",
        "lastAccessed": "2025-09-10T11:41:03.682Z"
    },
    {
        "key": "xs",
        "value": "48%3Ajg0SGQLh_poafg%3A2%3A1757504400%3A-1%3A-1",
        "domain": "facebook.com",
        "path": "/",
        "hostOnly": false,
        "creation": "2025-09-10T11:41:03.682Z",
        "lastAccessed": "2025-09-10T11:41:03.682Z"
    },
    {
        "key": "fr",
        "value": "0pVNczGSD5h070cwJ.AWdM4rsPYV8KXDKRpES_MPLlboQHYBe8HdV84Iur7HGCthC9DzE.Boulu6..AAA.0.0.BowWPJ.AWdLeYk2nJACH-H8p4OD6rzlJnk",
        "domain": "facebook.com",
        "path": "/",
        "hostOnly": false,
        "creation": "2025-09-10T11:41:03.682Z",
        "lastAccessed": "2025-09-10T11:41:03.682Z"
    },
    {
        "key": "fbl_st",
        "value": "101317189%3BT%3A29291740",
        "domain": "facebook.com",
        "path": "/",
        "hostOnly": false,
        "creation": "2025-09-10T11:41:03.682Z",
        "lastAccessed": "2025-09-10T11:41:03.682Z"
    },
    {
        "key": "wl_cbv",
        "value": "v2%3Bclient_version%3A2918%3Btimestamp%3A1757504459",
        "domain": "facebook.com",
        "path": "/",
        "hostOnly": false,
        "creation": "2025-09-10T11:41:03.682Z",
        "lastAccessed": "2025-09-10T11:41:03.682Z"
    }
]
